README.rst
setup.py
mezzanine_heroku/__init__.py
mezzanine_heroku/__version__.py
mezzanine_heroku/core.py
mezzanine_heroku/storage.py
mezzanine_heroku.egg-info/PKG-INFO
mezzanine_heroku.egg-info/SOURCES.txt
mezzanine_heroku.egg-info/dependency_links.txt
mezzanine_heroku.egg-info/requires.txt
mezzanine_heroku.egg-info/top_level.txt
test/test_mezzanine_heroku.py