Metadata-Version: 1.1
Name: mezzanine-heroku
Version: 0.3.19
Summary: This is a Mezzanine library for Heroku apps, a modification of django-heroku
Home-page: https://github.com/jackvz/mezzanine-heroku
Author: Jack van Zyl
Author-email: jackvanzyl@icloud.com
License: MIT
Platform: UNKNOWN
Classifier: License :: OSI Approved :: MIT License
Classifier: Programming Language :: Python :: 3.6
